{
	"ARMORS_SETS_ENABLED": {
		"EMERALD": true,
		"SOULDANCER": true,
		"FULL_METAL": true,
		"ENTERTAINER": true,
		"WITHER": true,
		"PLATE": true,
		"GOLDEN_PIGLIN": true,
		"FOX": true,
		"SCALE_MAIL": true,
		"REINFORCED_MAIL": true,
		"SHULKER": true,
		"ARCHER": true,
		"BATTLE": true,
		"THIEF": true,
		"RENEGADE": true,
		"CLIMBING_GEAR": true,
		"MYSTERY": true,
		"CHAMPION": true,
		"TROUBADOUR": true,
		"OCELOT": true,
		"LIVING_VINES": true,
		"PIGLIN": true,
		"GRIM": true,
		"GHOSTLY": true,
		"WOLF": true,
		"SOUL_ROBE": true,
		"GILDED": true,
		"HUNTER": true,
		"FROST": true,
		"OPULENT": true,
		"ARCTIC_FOX": true,
		"CURIOUS": true,
		"SPLENDID": true,
		"BLUE_MYSTERY": true,
		"BLACK_WOLF": true,
		"MERCENARY": true,
		"BEEHIVE": true,
		"TELEPORTATION": true,
		"GOURDIAN": true,
		"SPELUNKER": true,
		"GLOW_SQUID": true,
		"SPIDER": true,
		"BEENEST": true,
		"PURPLE_MYSTERY": true,
		"RUGGED_CLIMBING_GEAR": true,
		"HERO": true,
		"RED_MYSTERY": true,
		"UNSTABLE": true,
		"FROST_BITE": true,
		"EVOCATION": true,
		"HUNGRY_HORROR": true,
		"NIMBLE_TURTLE": true,
		"SPROUT": true,
		"GREEN_MYSTERY": true,
		"STURDY_SHULKER": true,
		"EMBER": true,
		"SQUID": true,
		"SWEET_TOOTH": true,
		"CAULDRON": true,
		"GOAT": true,
		"GHOST_KINDLER": true,
		"TURTLE": true,
		"SHADOW_WALKER": true,
		"ROYAL": true,
		"VERDANT": true,
		"VANGUARD": true,
		"HIGHLAND": true,
		"PHANTOM": true,
		"GUARDS": true,
		"DARK": true,
		"TITAN": true,
		"CAVE_CRAWLER": true,
		"SNOW": true,
		"STALWART_MAIL": true
	}
}